[1,["3cPh1p2wRKh4Vnz8CY2EiE","80+KYz5yFHMIivyIvdjFn7","b89BJt+H9AxLGvsJqxSvZs","43bTDE+kxMdos2MEzX13gh","440i36WLNBbb42opdoDCmd","81aVp8BXNJMLCrBXCc07r8","81pq2wT+xH2qMNdwQDZlSR","58pG7eNhtOKIVMBTSz7X+8"],["value"],[["cc.AnimationClip",["_name","_duration","curveData"],1,11]],[[0,0,1,2,3]],[[0,"Hero_Hurt",0.56,[{},"comps",11,[{},"cc.Sprite",11,[{},"spriteFrame",12,[[[{"frame":0},"value",6,0],[{"frame":0.07},"value",6,1],[{"frame":0.14},"value",6,2],[{"frame":0.21},"value",6,3],[{"frame":0.28},"value",6,4],[{"frame":0.35},"value",6,5],[{"frame":0.42},"value",6,6],[{"frame":0.48999998},"value",6,7]],11,11,11,11,11,11,11,11]]]]]],0,0,[0,0,0,0,0,0,0,0],[0,0,0,0,0,0,0,0],[0,1,2,3,4,5,6,7]]